[{"commit_id": null, "commit_url": null, "url": "https://api.github.com/repos/rust-lang/rust/issues/events/1198180470", "created_at": "2017-08-08T23:23:35Z", "actor": {"following_url": "https://api.github.com/users/sfackler/following{/other_user}", "events_url": "https://api.github.com/users/sfackler/events{/privacy}", "organizations_url": "https://api.github.com/users/sfackler/orgs", "url": "https://api.github.com/users/sfackler", "gists_url": "https://api.github.com/users/sfackler/gists{/gist_id}", "html_url": "https://github.com/sfackler", "subscriptions_url": "https://api.github.com/users/sfackler/subscriptions", "avatar_url": "https://avatars0.githubusercontent.com/u/1455697?v=4", "repos_url": "https://api.github.com/users/sfackler/repos", "received_events_url": "https://api.github.com/users/sfackler/received_events", "gravatar_id": "", "starred_url": "https://api.github.com/users/sfackler/starred{/owner}{/repo}", "site_admin": false, "login": "sfackler", "type": "User", "id": 1455697, "followers_url": "https://api.github.com/users/sfackler/followers"}, "event": "labeled", "label": {"color": "e102d8", "name": "B-unstable"}, "id": 1198180470}, {"commit_id": null, "commit_url": null, "url": "https://api.github.com/repos/rust-lang/rust/issues/events/1198180471", "created_at": "2017-08-08T23:23:35Z", "actor": {"following_url": "https://api.github.com/users/sfackler/following{/other_user}", "events_url": "https://api.github.com/users/sfackler/events{/privacy}", "organizations_url": "https://api.github.com/users/sfackler/orgs", "url": "https://api.github.com/users/sfackler", "gists_url": "https://api.github.com/users/sfackler/gists{/gist_id}", "html_url": "https://github.com/sfackler", "subscriptions_url": "https://api.github.com/users/sfackler/subscriptions", "avatar_url": "https://avatars0.githubusercontent.com/u/1455697?v=4", "repos_url": "https://api.github.com/users/sfackler/repos", "received_events_url": "https://api.github.com/users/sfackler/received_events", "gravatar_id": "", "starred_url": "https://api.github.com/users/sfackler/starred{/owner}{/repo}", "site_admin": false, "login": "sfackler", "type": "User", "id": 1455697, "followers_url": "https://api.github.com/users/sfackler/followers"}, "event": "labeled", "label": {"color": "bfd4f2", "name": "T-libs"}, "id": 1198180471}, {"commit_id": null, "commit_url": null, "url": "https://api.github.com/repos/rust-lang/rust/issues/events/1199929751", "created_at": "2017-08-09T21:46:54Z", "actor": {"following_url": "https://api.github.com/users/notriddle/following{/other_user}", "events_url": "https://api.github.com/users/notriddle/events{/privacy}", "organizations_url": "https://api.github.com/users/notriddle/orgs", "url": "https://api.github.com/users/notriddle", "gists_url": "https://api.github.com/users/notriddle/gists{/gist_id}", "html_url": "https://github.com/notriddle", "subscriptions_url": "https://api.github.com/users/notriddle/subscriptions", "avatar_url": "https://avatars1.githubusercontent.com/u/1593513?v=4", "repos_url": "https://api.github.com/users/notriddle/repos", "received_events_url": "https://api.github.com/users/notriddle/received_events", "gravatar_id": "", "starred_url": "https://api.github.com/users/notriddle/starred{/owner}{/repo}", "site_admin": false, "login": "notriddle", "type": "User", "id": 1593513, "followers_url": "https://api.github.com/users/notriddle/followers"}, "event": "mentioned", "id": 1199929751}, {"commit_id": null, "commit_url": null, "url": "https://api.github.com/repos/rust-lang/rust/issues/events/1199929752", "created_at": "2017-08-09T21:46:54Z", "actor": {"following_url": "https://api.github.com/users/notriddle/following{/other_user}", "events_url": "https://api.github.com/users/notriddle/events{/privacy}", "organizations_url": "https://api.github.com/users/notriddle/orgs", "url": "https://api.github.com/users/notriddle", "gists_url": "https://api.github.com/users/notriddle/gists{/gist_id}", "html_url": "https://github.com/notriddle", "subscriptions_url": "https://api.github.com/users/notriddle/subscriptions", "avatar_url": "https://avatars1.githubusercontent.com/u/1593513?v=4", "repos_url": "https://api.github.com/users/notriddle/repos", "received_events_url": "https://api.github.com/users/notriddle/received_events", "gravatar_id": "", "starred_url": "https://api.github.com/users/notriddle/starred{/owner}{/repo}", "site_admin": false, "login": "notriddle", "type": "User", "id": 1593513, "followers_url": "https://api.github.com/users/notriddle/followers"}, "event": "subscribed", "id": 1199929752}, {"commit_id": null, "commit_url": null, "url": "https://api.github.com/repos/rust-lang/rust/issues/events/1201112416", "created_at": "2017-08-10T15:04:24Z", "actor": {"following_url": "https://api.github.com/users/Mark-Simulacrum/following{/other_user}", "events_url": "https://api.github.com/users/Mark-Simulacrum/events{/privacy}", "organizations_url": "https://api.github.com/users/Mark-Simulacrum/orgs", "url": "https://api.github.com/users/Mark-Simulacrum", "gists_url": "https://api.github.com/users/Mark-Simulacrum/gists{/gist_id}", "html_url": "https://github.com/Mark-Simulacrum", "subscriptions_url": "https://api.github.com/users/Mark-Simulacrum/subscriptions", "avatar_url": "https://avatars0.githubusercontent.com/u/5047365?v=4", "repos_url": "https://api.github.com/users/Mark-Simulacrum/repos", "received_events_url": "https://api.github.com/users/Mark-Simulacrum/received_events", "gravatar_id": "", "starred_url": "https://api.github.com/users/Mark-Simulacrum/starred{/owner}{/repo}", "site_admin": false, "login": "Mark-Simulacrum", "type": "User", "id": 5047365, "followers_url": "https://api.github.com/users/Mark-Simulacrum/followers"}, "event": "labeled", "label": {"color": "f5f1fd", "name": "C-tracking-issue"}, "id": 1201112416}, {"commit_id": null, "commit_url": null, "url": "https://api.github.com/repos/rust-lang/rust/issues/events/1210595219", "created_at": "2017-08-17T17:44:34Z", "actor": {"following_url": "https://api.github.com/users/notriddle/following{/other_user}", "events_url": "https://api.github.com/users/notriddle/events{/privacy}", "organizations_url": "https://api.github.com/users/notriddle/orgs", "url": "https://api.github.com/users/notriddle", "gists_url": "https://api.github.com/users/notriddle/gists{/gist_id}", "html_url": "https://github.com/notriddle", "subscriptions_url": "https://api.github.com/users/notriddle/subscriptions", "avatar_url": "https://avatars1.githubusercontent.com/u/1593513?v=4", "repos_url": "https://api.github.com/users/notriddle/repos", "received_events_url": "https://api.github.com/users/notriddle/received_events", "gravatar_id": "", "starred_url": "https://api.github.com/users/notriddle/starred{/owner}{/repo}", "site_admin": false, "login": "notriddle", "type": "User", "id": 1593513, "followers_url": "https://api.github.com/users/notriddle/followers"}, "event": "mentioned", "id": 1210595219}, {"commit_id": null, "commit_url": null, "url": "https://api.github.com/repos/rust-lang/rust/issues/events/1210595222", "created_at": "2017-08-17T17:44:34Z", "actor": {"following_url": "https://api.github.com/users/notriddle/following{/other_user}", "events_url": "https://api.github.com/users/notriddle/events{/privacy}", "organizations_url": "https://api.github.com/users/notriddle/orgs", "url": "https://api.github.com/users/notriddle", "gists_url": "https://api.github.com/users/notriddle/gists{/gist_id}", "html_url": "https://github.com/notriddle", "subscriptions_url": "https://api.github.com/users/notriddle/subscriptions", "avatar_url": "https://avatars1.githubusercontent.com/u/1593513?v=4", "repos_url": "https://api.github.com/users/notriddle/repos", "received_events_url": "https://api.github.com/users/notriddle/received_events", "gravatar_id": "", "starred_url": "https://api.github.com/users/notriddle/starred{/owner}{/repo}", "site_admin": false, "login": "notriddle", "type": "User", "id": 1593513, "followers_url": "https://api.github.com/users/notriddle/followers"}, "event": "subscribed", "id": 1210595222}, {"commit_id": null, "commit_url": null, "url": "https://api.github.com/repos/rust-lang/rust/issues/events/1211149944", "created_at": "2017-08-18T01:21:33Z", "actor": {"following_url": "https://api.github.com/users/earthengine/following{/other_user}", "events_url": "https://api.github.com/users/earthengine/events{/privacy}", "organizations_url": "https://api.github.com/users/earthengine/orgs", "url": "https://api.github.com/users/earthengine", "gists_url": "https://api.github.com/users/earthengine/gists{/gist_id}", "html_url": "https://github.com/earthengine", "subscriptions_url": "https://api.github.com/users/earthengine/subscriptions", "avatar_url": "https://avatars2.githubusercontent.com/u/2227031?v=4", "repos_url": "https://api.github.com/users/earthengine/repos", "received_events_url": "https://api.github.com/users/earthengine/received_events", "gravatar_id": "", "starred_url": "https://api.github.com/users/earthengine/starred{/owner}{/repo}", "site_admin": false, "login": "earthengine", "type": "User", "id": 2227031, "followers_url": "https://api.github.com/users/earthengine/followers"}, "event": "mentioned", "id": 1211149944}, {"commit_id": null, "commit_url": null, "url": "https://api.github.com/repos/rust-lang/rust/issues/events/1211149945", "created_at": "2017-08-18T01:21:33Z", "actor": {"following_url": "https://api.github.com/users/earthengine/following{/other_user}", "events_url": "https://api.github.com/users/earthengine/events{/privacy}", "organizations_url": "https://api.github.com/users/earthengine/orgs", "url": "https://api.github.com/users/earthengine", "gists_url": "https://api.github.com/users/earthengine/gists{/gist_id}", "html_url": "https://github.com/earthengine", "subscriptions_url": "https://api.github.com/users/earthengine/subscriptions", "avatar_url": "https://avatars2.githubusercontent.com/u/2227031?v=4", "repos_url": "https://api.github.com/users/earthengine/repos", "received_events_url": "https://api.github.com/users/earthengine/received_events", "gravatar_id": "", "starred_url": "https://api.github.com/users/earthengine/starred{/owner}{/repo}", "site_admin": false, "login": "earthengine", "type": "User", "id": 2227031, "followers_url": "https://api.github.com/users/earthengine/followers"}, "event": "subscribed", "id": 1211149945}]